README.md
pyproject.toml
ommx_pyscipopt_adapter/__init__.py
ommx_pyscipopt_adapter/adapter.py
ommx_pyscipopt_adapter/exception.py
ommx_pyscipopt_adapter.egg-info/PKG-INFO
ommx_pyscipopt_adapter.egg-info/SOURCES.txt
ommx_pyscipopt_adapter.egg-info/dependency_links.txt
ommx_pyscipopt_adapter.egg-info/requires.txt
ommx_pyscipopt_adapter.egg-info/top_level.txt
tests/test_error.py
tests/test_initial_state.py
tests/test_integration.py
tests/test_ommx_pyscipopt.py
tests/test_sos1_partial_evaluate.py
tests/test_sos1_working.py