Metadata-Version: 2.4
Name: ommx_pyscipopt_adapter
Version: 2.3.4
Summary: An adapter for the SCIP from OMMX.
Author-email: "Jij Inc." <info@j-ij.com>
Project-URL: Repository, https://github.com/Jij-Inc/ommx
Project-URL: Issues, https://github.com/Jij-Inc/ommx/issues
Classifier: Programming Language :: Python :: 3 :: Only
Classifier: Programming Language :: Python :: 3.10
Classifier: Programming Language :: Python :: 3.11
Classifier: Programming Language :: Python :: 3.12
Classifier: Programming Language :: Python :: 3.13
Classifier: License :: OSI Approved :: Apache Software License
Classifier: License :: OSI Approved :: MIT License
Requires-Python: <3.14,>=3.10
Requires-Dist: ommx<3.0.0,>=2.0.0b3
Requires-Dist: PySCIPOpt<7.0.0,>=6.0.0
